redmage/__init__.py
redmage/components.py
redmage/convertors.py
redmage/core.py
redmage/elements.py
redmage/exceptions.py
redmage/py.typed
redmage/targets.py
redmage/triggers.py
redmage/types.py
redmage/utils.py
redmage-0.5.0.dist-info/LICENSE
redmage-0.5.0.dist-info/METADATA
redmage-0.5.0.dist-info/WHEEL
redmage-0.5.0.dist-info/RECORD
