Metadata-Version: 2.1
Name: redmage
Version: 0.5.0
Summary: A component based library for building htmx powered applications.
License: MIT
Author: Scott Russell
Author-email: me@scottrussell.net
Requires-Python: >=3.8,<4.0
Classifier: License :: OSI Approved :: MIT License
Classifier: Programming Language :: Python :: 3
Classifier: Programming Language :: Python :: 3.8
Classifier: Programming Language :: Python :: 3.9
Classifier: Programming Language :: Python :: 3.10
Classifier: Programming Language :: Python :: 3.11
Classifier: Programming Language :: Python :: 3.12
Requires-Dist: hype-html (>=2.1.2,<3.0.0)
Requires-Dist: python-multipart (>=0.0.6,<0.0.7)
Requires-Dist: starlette (>=0.26.1,<0.27.0)
